MANIFEST.in
membership_demo.xml
membership_view.xml
setup.py
./__init__.py
./__openerp__.py
./membership.py
./report/__init__.py
./report/report_membership.py
./wizard/__init__.py
./wizard/membership_invoice.py
i18n/ar.po
i18n/bg.po
i18n/bs.po
i18n/ca.po
i18n/cs.po
i18n/da.po
i18n/de.po
i18n/es.po
i18n/es_AR.po
i18n/es_CR.po
i18n/es_MX.po
i18n/es_VE.po
i18n/et.po
i18n/fi.po
i18n/fr.po
i18n/gl.po
i18n/hr.po
i18n/hu.po
i18n/id.po
i18n/it.po
i18n/ja.po
i18n/ko.po
i18n/lt.po
i18n/membership.pot
i18n/mk.po
i18n/mn.po
i18n/nl.po
i18n/nl_BE.po
i18n/pl.po
i18n/pt.po
i18n/pt_BR.po
i18n/ro.po
i18n/ru.po
i18n/sk.po
i18n/sl.po
i18n/sq.po
i18n/sr@latin.po
i18n/sv.po
i18n/tlh.po
i18n/tr.po
i18n/uk.po
i18n/vi.po
i18n/zh_CN.po
i18n/zh_TW.po
images/members.jpeg
images/membership_list.jpeg
images/membership_products.jpeg
openerp_membership.egg-info/PKG-INFO
openerp_membership.egg-info/SOURCES.txt
openerp_membership.egg-info/dependency_links.txt
openerp_membership.egg-info/requires.txt
openerp_membership.egg-info/top_level.txt
process/membership_process.xml
report/report_membership_view.xml
security/ir.model.access.csv
test/test_membership.yml
wizard/membership_invoice_view.xml